viridicle/_C.cpython-39-x86_64-linux-gnu.so
viridicle/__init__.py
viridicle/viridicle.py
viridicle/utils.py
viridicle-0.1.1.dist-info/top_level.txt
viridicle-0.1.1.dist-info/WHEEL
viridicle-0.1.1.dist-info/COPYING.md
viridicle-0.1.1.dist-info/RECORD
viridicle-0.1.1.dist-info/METADATA
