Metadata-Version: 2.1
Name: viridicle
Version: 0.1.1
Summary: Fast stochastic ecological simulations on graphs in Python and numpy
Home-page: https://github.com/TheoremEngine/viridicle
Author: Mark Lowell
License: UNKNOWN
Platform: UNKNOWN
Classifier: Intended Audience :: Science/Research
Classifier: License :: OSI Approved :: GNU General Public License v3 or later (GPLv3+)
Classifier: Programming Language :: Python :: 3
Classifier: Topic :: Scientific/Engineering :: Mathematics
Requires-Python: >=3.6
Requires-Dist: networkx
Requires-Dist: numpy
